__init__.py
ldif2json.py
ldif2json-1.0.8.dist-info/licenses/LICENSE
ldif2json-1.0.8.dist-info/METADATA
ldif2json-1.0.8.dist-info/WHEEL
ldif2json-1.0.8.dist-info/entry_points.txt
ldif2json-1.0.8.dist-info/top_level.txt
ldif2json-1.0.8.dist-info/RECORD
