Metadata-Version: 2.4
Name: ldif2json
Version: 1.0.8
Summary: A robust Python tool for converting LDAP Data Interchange Format (LDIF) files to JSON with support for hierarchical nesting and Base64 decoding.
Author-email: Jairsinho Ramirez Ruiz <jairsinho@gmail.com>
License-Expression: MIT
Project-URL: Homepage, https://github.com/jairsinho/ldif2json
Project-URL: Documentation, https://github.com/jairsinho/ldif2json#readme
Project-URL: BugTracker, https://github.com/jairsinho/ldif2json/issues
Classifier: Development Status :: 5 - Production/Stable
Classifier: Intended Audience :: Developers
Classifier: Intended Audience :: System Administrators
Classifier: Programming Language :: Python :: 3
Classifier: Programming Language :: Python :: 3.9
Classifier: Programming Language :: Python :: 3.10
Classifier: Programming Language :: Python :: 3.11
Classifier: Programming Language :: Python :: 3.12
Classifier: Topic :: Software Development :: Libraries :: Python Modules
Classifier: Topic :: System :: Systems Administration :: Authentication/Directory :: LDAP
Requires-Python: >=3.9
License-File: LICENSE
Provides-Extra: test
Requires-Dist: pytest>=7.0; extra == "test"
Requires-Dist: pytest-cov>=4.0; extra == "test"
Dynamic: license-file
